setup.py
seeta_helper.egg-info/PKG-INFO
seeta_helper.egg-info/SOURCES.txt
seeta_helper.egg-info/dependency_links.txt
seeta_helper.egg-info/entry_points.txt
seeta_helper.egg-info/requires.txt
seeta_helper.egg-info/top_level.txt
seetaas_helper/__init__.py
seetaas_helper/base.py
seetaas_helper/config.py
seetaas_helper/dataset.py
seetaas_helper/deploy.py
seetaas_helper/metric.py
seetaas_helper/progress.py
seetaas_helper/result.py