Metadata-Version: 1.2
Name: seeta-helper
Version: 0.0.5
Summary: SeeTaaS helper functions
Home-page: UNKNOWN
Maintainer-email: seetaas@seetatech.com
License: UNKNOWN
Platform: any
Classifier: Programming Language :: Python
Classifier: Operating System :: OS Independent
